FedTools/Beigebook.py
FedTools/FedMins.py
FedTools/FedMinutes.py
FedTools/__init__.py
Fedtools-0.0.7.dist-info/METADATA
Fedtools-0.0.7.dist-info/WHEEL
Fedtools-0.0.7.dist-info/top_level.txt
Fedtools-0.0.7.dist-info/RECORD
