Metadata-Version: 2.1
Name: Fedtools
Version: 0.0.7
Summary: An open source library for the extraction of Federal Reserve Data.
Author: David Woroniuk
Author-email: david.woroniuk@durham.ac.uk
License: MIT
Requires-Dist: numpy
Requires-Dist: pandas
Requires-Dist: requests
Requires-Dist: beautifulsoup4
Requires-Dist: fake-useragent
Requires-Dist: python-dateutil
Requires-Dist: pytz
Requires-Dist: six
Requires-Dist: soupsieve
